automatic_crud/__init__.py
automatic_crud/base_report.py
automatic_crud/data_types.py
automatic_crud/generics.py
automatic_crud/models.py
automatic_crud/register.py
automatic_crud/response_messages.py
automatic_crud/urls.py
automatic_crud/utils.py
automatic_crud/views_crud.py
automatic_crud/views_crud_ajax.py
django_automatic_crud-1.2.0.dist-info/LICENSE.txt
django_automatic_crud-1.2.0.dist-info/METADATA
django_automatic_crud-1.2.0.dist-info/WHEEL
django_automatic_crud-1.2.0.dist-info/top_level.txt
django_automatic_crud-1.2.0.dist-info/RECORD
